kakeibox_database_dictionary/__init__.py
kakeibox_database_dictionary/database/__init__.py
kakeibox_database_dictionary/database/account.py
kakeibox_database_dictionary/database/transaction.py
kakeibox_database_dictionary/database/transaction_category.py
kakeibox_database_dictionary/database/transaction_subcategory.py
kakeibox_database_dictionary/engine/__init__.py
tests/__init__.py
tests/conftest.py
tests/test_architecture.py
tests/test_engine.py
tests/database/__init__.py
tests/database/test_account.py
tests/database/test_transaction.py
tests/database/test_transaction_category.py
tests/database/test_transaction_subcategory.py
tests/fixtures/__init__.py
tests/fixtures/transaction_data.py
kakeibox_database_dictionary-1.0.0.dist-info/AUTHORS.rst
kakeibox_database_dictionary-1.0.0.dist-info/LICENSE
kakeibox_database_dictionary-1.0.0.dist-info/METADATA
kakeibox_database_dictionary-1.0.0.dist-info/WHEEL
kakeibox_database_dictionary-1.0.0.dist-info/top_level.txt
kakeibox_database_dictionary-1.0.0.dist-info/RECORD
